pyCDTT/__init__.py
pyCDTT/cmd.py
pyCDTT/delete.py
pyCDTT-0.0.1.dist-info/METADATA
pyCDTT-0.0.1.dist-info/WHEEL
pyCDTT-0.0.1.dist-info/top_level.txt
pyCDTT-0.0.1.dist-info/RECORD
