Metadata-Version: 2.1
Name: pyCDTT
Version: 0.0.1
Summary: 这是CDT的工具包模块！
Author: CDT
Author-email: ZMF_CDT-1@outlook.com
License: UNKNOWN
Platform: UNKNOWN
Classifier: Programming Language :: Python :: 3
Classifier: License :: OSI Approved :: MIT License
Classifier: Operating System :: OS Independent
Requires-Python: >=3
